regenerator/__init__.py
regenerator/_version.py
regenerator/core.py
regenerator-0.1.2.dist-info/licenses/LICENSE
regenerator-0.1.2.dist-info/METADATA
regenerator-0.1.2.dist-info/WHEEL
regenerator-0.1.2.dist-info/top_level.txt
regenerator-0.1.2.dist-info/RECORD
