Metadata-Version: 2.4
Name: regenerator
Version: 0.1.2
Summary: Simple class for reusable generators.
Author: pommevoid
License-Expression: MIT
Project-URL: Homepage, https://github.com/pommevoid/regenerator
Requires-Python: >=3.8
License-File: LICENSE
Dynamic: license-file
